kmonitor/__init__.py
kmonitor/_ver.py
kmonitor/base.py
kmonitor/mixins/nodes_mixin.py
kmonitor/mixins/pods_mixin.py
kmonitor/utils/consts.py
kmonitor/utils/util.py
kmonitor-0.2.11.dist-info/METADATA
kmonitor-0.2.11.dist-info/WHEEL
kmonitor-0.2.11.dist-info/licenses/LICENSE
kmonitor-0.2.11.dist-info/RECORD
