Metadata-Version: 2.3
Name: kmonitor
Version: 0.2.11
Summary: kmonitor is a simple utility wrapper around kubernetes package
Project-URL: Homepage, https://github.com/aidamian/k8s_monitor
Project-URL: Bug Tracker, https://github.com/aidamian/k8s_monitor/issues
Author-email: Andrei Ionut Damian <andrei.damian@me.com>
Classifier: License :: OSI Approved :: MIT License
Classifier: Operating System :: OS Independent
Classifier: Programming Language :: Python :: 3
Requires-Python: >=3.8
Requires-Dist: kubernetes
